LatticeFinder/__init__.py
LatticeFinder/LatticeFinder/Create_submitSL_slurm_Main.py
LatticeFinder/LatticeFinder/LatticeFinder.py
LatticeFinder/LatticeFinder/examining_lattice_constant_methods_with_ASE.py
LatticeFinder/LatticeFinder/examining_lattice_constant_methods_with_Manual_Mode.py
LatticeFinder/LatticeFinder/examining_lattice_constant_methods_with_VASP.py
LatticeFinder/LatticeFinder/lattice_constant_generator.py
LatticeFinder/LatticeFinder/other_methods.py
LatticeFinder/LatticeFinder/plotting_methods.py
LatticeFinder/Subsidiary_Programs/LatticeFinder_Tidy_Finished_Jobs.py
LatticeFinder/Subsidiary_Programs/Run_LatticeFinder_submitSL_slurm.py
LatticeFinder/Subsidiary_Programs/Run_overall_LatticeFinder_submitSL_slurm.py
LatticeFinder-1.1.2.4.dist-info/LICENSE
LatticeFinder-1.1.2.4.dist-info/METADATA
LatticeFinder-1.1.2.4.dist-info/WHEEL
LatticeFinder-1.1.2.4.dist-info/top_level.txt
LatticeFinder-1.1.2.4.dist-info/RECORD
