Metadata-Version: 2.1
Name: LatticeFinder
Version: 1.1.2.4
Summary: This program is designed to give the lattice constants for a 3D crystal lattice or a 2D system, such as graphene (in development).
Home-page: https://blogs.otago.ac.nz/annagarden/
Author: Geoffrey R. Weal and Dr. Anna L. Garden
Author-email: anna.garden@otago.ac.nz
License: GNU AFFERO GENERAL PUBLIC LICENSE
Download-URL: https://github.com/GardenGroupUO/LatticeFinder/archive/v1.1.2.4.tar.gz
Keywords: lattice,lattice_constant,ase,university-of-otago,asap3,atomic-simulation-environment,jupyter-binder,otago-university
Platform: UNKNOWN
Classifier: Development Status :: 3 - Alpha
Classifier: Intended Audience :: Science/Research
Classifier: Natural Language :: English
Classifier: Operating System :: MacOS :: MacOS X
Classifier: Operating System :: POSIX :: Linux
Classifier: Operating System :: Unix
Classifier: Topic :: Scientific/Engineering :: Chemistry
Classifier: Topic :: Scientific/Engineering :: Physics
Classifier: Topic :: Scientific/Engineering :: Mathematics
Classifier: Topic :: Scientific/Engineering :: Artificial Intelligence
Classifier: Natural Language :: English
Classifier: License :: OSI Approved :: GNU Affero General Public License v3
Classifier: Programming Language :: Python :: 3 :: Only
Classifier: Programming Language :: Python :: 3.6
Classifier: Programming Language :: Python :: 3.7
Classifier: Programming Language :: Python :: 3.8
Classifier: Programming Language :: Python :: 3.9
Requires-Dist: numpy
Requires-Dist: scipy
Requires-Dist: matplotlib
Requires-Dist: ase (>=3.19.0)
